LICENSE
MANIFEST.in
README.md
setup.py
calltoaction/__init__.py
calltoaction/admin.py
calltoaction/cms_plugins.py
calltoaction/models.py
calltoaction/settings.py
calltoaction/migrations/0001_initial.py
calltoaction/migrations/0002_auto_20150731_1202.py
calltoaction/migrations/0003_auto_20151027_1005.py
calltoaction/migrations/__init__.py
calltoaction/templates/calltoaction/default.html
calltoaction/templatetags/__init__.py
calltoaction/templatetags/calltoaction_tags.py
djangocms_calltoaction.egg-info/PKG-INFO
djangocms_calltoaction.egg-info/SOURCES.txt
djangocms_calltoaction.egg-info/dependency_links.txt
djangocms_calltoaction.egg-info/requires.txt
djangocms_calltoaction.egg-info/top_level.txt