Metadata-Version: 1.1
Name: djangocms-calltoaction
Version: 0.8.4
Summary: djangocms plugin for managing lead generation calls to action
Home-page: https://github.com/logithr/djangocms-calltoaction
Author: Sasha Matijasic
Author-email: sasha@selectnull.com
License: MIT
Platform: UNKNOWN
Classifier: Development Status :: 4 - Beta
Classifier: Environment :: Web Environment
Classifier: Framework :: Django
Classifier: Intended Audience :: Developers
Classifier: License :: OSI Approved :: MIT License
Classifier: Operating System :: OS Independent
Classifier: Programming Language :: Python
Classifier: Programming Language :: Python :: 2
Classifier: Programming Language :: Python :: 2.7
Classifier: Topic :: Internet :: WWW/HTTP :: Dynamic Content
